README.md
setup.py
caict_sync_testsuite.egg-info/PKG-INFO
caict_sync_testsuite.egg-info/SOURCES.txt
caict_sync_testsuite.egg-info/dependency_links.txt
caict_sync_testsuite.egg-info/requires.txt
caict_sync_testsuite.egg-info/top_level.txt
core/__init__.py
core/client_flask_img.py
core/infer.py
core/infer_label.py
core/mq_write.py
core/oss_upload_img.py
core/pic_snapshots.py
core/restfuL_api.py
core/send_email.py
core/send_msg.py
core/server_ai_xunjian.py