Metadata-Version: 2.1
Name: caict-sync-testsuite
Version: 1.0
Summary: smart AI detection project of sync.
Home-page: https://github.com/lvboodvl/smart_sync.git
Author: Bo Lv
Author-email: fengdieer_13@126.com
License: MIT
Platform: UNKNOWN
Classifier: License :: OSI Approved :: MIT License
Classifier: Programming Language :: Python
Classifier: Programming Language :: Python :: 3
Classifier: Programming Language :: Python :: 3.6
Classifier: Programming Language :: Python :: Implementation :: CPython
Classifier: Programming Language :: Python :: Implementation :: PyPy
Requires-Python: >=3.6.0
